flask_restify/__init__.py
flask_restify/jsons.py
flask_restify/packable.py
Flask_RESTify-0.1.3.dist-info/DESCRIPTION.rst
Flask_RESTify-0.1.3.dist-info/METADATA
Flask_RESTify-0.1.3.dist-info/metadata.json
Flask_RESTify-0.1.3.dist-info/RECORD
Flask_RESTify-0.1.3.dist-info/top_level.txt
Flask_RESTify-0.1.3.dist-info/WHEEL
