Metadata-Version: 2.0
Name: Flask-RESTify
Version: 0.1.3
Summary: Flask REST framework
Home-page: https://github.com/cllu/Flask-RESTify
Author: Chunliang Lyu
Author-email: hi@chunlianglyu.com
License: BSD
Keywords: Flask-RESTify
Platform: UNKNOWN
Classifier: Development Status :: 2 - Pre-Alpha
Classifier: Intended Audience :: Developers
Classifier: License :: OSI Approved :: BSD License
Classifier: Natural Language :: English
Classifier: Programming Language :: Python :: 2
Classifier: Programming Language :: Python :: 2.6
Classifier: Programming Language :: Python :: 2.7
Classifier: Programming Language :: Python :: 3
Classifier: Programming Language :: Python :: 3.3
Classifier: Programming Language :: Python :: 3.4
